[
  {
    "name": "theme_info",
    "theme_name": "Thrivve Labs",
    "theme_version": "1.0.0",
    "theme_author": "Thrivve Labs"
  },
  {
    "name": "Colors",
    "settings": [
      {
        "type": "header",
        "content": "Base"
      },
      {
        "type": "color",
        "id": "color_bg_void",
        "label": "Background (void)",
        "default": "#0A0A0B"
      },
      {
        "type": "color",
        "id": "color_bg_panel",
        "label": "Background (panel)",
        "default": "#141416"
      },
      {
        "type": "color",
        "id": "color_bg_panel_raised",
        "label": "Background (raised panel)",
        "default": "#1C1C1F"
      },
      {
        "type": "header",
        "content": "Accent - Red Light"
      },
      {
        "type": "color",
        "id": "color_red_core",
        "label": "Red core (primary accent)",
        "default": "#FF2A3A"
      },
      {
        "type": "color",
        "id": "color_red_glow",
        "label": "Red glow (hover/light)",
        "default": "#FF4D5E"
      },
      {
        "type": "color",
        "id": "color_ember",
        "label": "Ember (deep red-black)",
        "default": "#2A0A0D"
      },
      {
        "type": "header",
        "content": "Text"
      },
      {
        "type": "color",
        "id": "color_text_primary",
        "label": "Text primary",
        "default": "#F5F4F2"
      },
      {
        "type": "color",
        "id": "color_text_muted",
        "label": "Text muted",
        "default": "#8A8890"
      },
      {
        "type": "color",
        "id": "color_border",
        "label": "Border",
        "default": "#2A2A2D"
      }
    ]
  },
  {
    "name": "Typography",
    "settings": [
      {
        "type": "header",
        "content": "Display font"
      },
      {
        "type": "font_picker",
        "id": "font_display",
        "label": "Display font",
        "default": "syne_n4"
      },
      {
        "type": "header",
        "content": "Body font"
      },
      {
        "type": "font_picker",
        "id": "font_body",
        "label": "Body font",
        "default": "inter_n4"
      }
    ]
  }
]
